{
    "keep": {
        "days": true,
        "amount": 14
    },
    "auditLog": "E:\\mobile_app_development\\xephyr-lab\\logs\\winston\\successes\\.31e6041b82e62afefbdc9d71af9d496967da92a0-audit.json",
    "files": [
        {
            "date": 1736812613308,
            "name": "E:\\mobile_app_development\\xephyr-lab\\logs\\winston\\successes\\phu-2025-01-14-05-success.log",
            "hash": "e6019371d73b98a34ee204195379c4c867841c9cbf59cbc6abf99f17196376e1"
        },
        {
            "date": 1736814020704,
            "name": "E:\\mobile_app_development\\xephyr-lab\\logs\\winston\\successes\\phu-2025-01-14-06-success.log",
            "hash": "405f46e9f1b07f5ff677dd6719f3e877a29877492dbf180672280d1e80a033e5"
        },
        {
            "date": 1736816915495,
            "name": "E:\\mobile_app_development\\xephyr-lab\\logs\\winston\\successes\\phu-2025-01-14-07-success.log",
            "hash": "530b3af98d5b827ee87361cf089412fd5ba67b2690cb4f96237f8c02874f75f8"
        },
        {
            "date": 1736820101132,
            "name": "E:\\mobile_app_development\\xephyr-lab\\logs\\winston\\successes\\phu-2025-01-14-08-success.log",
            "hash": "e55a9b429470888a3fe833d9a92019978f03b67bcbc5cd3f101ea84ceb8ed653"
        }
    ],
    "hashType": "sha256"
}